bartpy2/__init__.py
bartpy2/data.py
bartpy2/errors.py
bartpy2/model.py
bartpy2/mutation.py
bartpy2/node.py
bartpy2/plotting.py
bartpy2/sigma.py
bartpy2/sklearnmodel.py
bartpy2/split.py
bartpy2/tree.py
bartpy2/diagnostics/__init__.py
bartpy2/diagnostics/features.py
bartpy2/diagnostics/trees.py
bartpy2/extensions/__init__.py
bartpy2/extensions/baseestimator.py
bartpy2/extensions/ols.py
bartpy2/samplers/__init__.py
bartpy2/samplers/leafnode.py
bartpy2/samplers/modelsampler.py
bartpy2/samplers/sampler.py
bartpy2/samplers/schedule.py
bartpy2/samplers/sigma.py
bartpy2/samplers/treemutation/__init__.py
bartpy2/samplers/treemutation/likihoodratio.py
bartpy2/samplers/treemutation/proposer.py
bartpy2/samplers/treemutation/treemutation.py
bartpy2/samplers/treemutation/uniform/__init__.py
bartpy2/samplers/treemutation/uniform/likihoodratio.py
bartpy2/samplers/treemutation/uniform/proposer.py
bartpy2-0.0.2.dist-info/LICENSE
bartpy2-0.0.2.dist-info/METADATA
bartpy2-0.0.2.dist-info/WHEEL
bartpy2-0.0.2.dist-info/top_level.txt
bartpy2-0.0.2.dist-info/RECORD
